api_master/__init__.py
api_master/cfg.py
api_master/myconfig.py
api_master/quick_start.py
api_master/test.py
api_master/_discord/__init__.py
api_master/_discord/discord_stock_example.py
api_master/_discord/discord_stock_market.py
api_master/_discord/embeddings.py
api_master/_discord/emojis.py
api_master/_discord/live_discord.py
api_master/_discord/webhook_creation.py
api_master/_discord/hooks/__init__.py
api_master/_discord/hooks/channel_webhooks.py
api_master/_discord/hooks/hook_dicts.py
api_master/_discord/hooks/send_webhook.py
api_master/_discord/views/__init__.py
api_master/bot/__init__.py
api_master/bot/autocomp.py
api_master/bot/discord_emojis.py
api_master/bot/helpers.py
api_master/bot/main.py
api_master/bot/options_market.py
api_master/bot/stock_market.py
api_master/bot/app/__init__.py
api_master/bot/app/command.py
api_master/bot/app/datalists.py
api_master/bot/app/filter_functions.py
api_master/bot/app/fudstop.py
api_master/bot/app/funcs.py
api_master/bot/app/helper_functions.py
api_master/bot/utils/__init__.py
api_master/bot/utils/crypto_coins.py
api_master/bot/utils/date_times.py
api_master/bot/utils/lists_and_dicts.py
api_master/bot/utils/technicals.py
api_master/bot/utils/webull_tickers.py
api_master/bot/views/__init__.py
api_master/bot/views/learnviews.py
api_master/bot/views/mainview.py
api_master/examples/__init__.py
api_master/examples/fed_Rrepo_propositions.py
api_master/examples/fed_agency_mbs.py
api_master/examples/fed_counterparties.py
api_master/examples/fed_fxswaps.py
api_master/examples/fed_repo_operations.py
api_master/examples/fed_securities_lending.py
api_master/examples/helpers.py
api_master/examples/nasdaq_bigmac.py
api_master/examples/nasdaq_economic_indicators.py
api_master/examples/nasdaq_gdp.py
api_master/examples/nasdaq_income_expenditures.py
api_master/examples/nasdaq_inflation.py
api_master/examples/nasdaq_interest_rates.py
api_master/examples/nasdaq_repos.py
api_master/examples/nasdaq_sp500.py
api_master-1.11.dist-info/METADATA
api_master-1.11.dist-info/WHEEL
api_master-1.11.dist-info/top_level.txt
api_master-1.11.dist-info/RECORD
