Metadata-Version: 2.1
Name: api-master
Version: 1.11
Summary: Utilize several market-data APIs in production-ready format for real-time and simulated market analysis.
Home-page: https://github.com/chuckdustin12/polygonsdk
Author: Chuck Dustin
Author-email: chuckdustin12@gmail.com
Keywords: trading,stocks,options,crypto,forex,indices,discord
Classifier: License :: OSI Approved :: MIT License
Classifier: Programming Language :: Python :: 3
